client_package/__init__.py
client_package/client.py
my_messenger_client-0.1.dist-info/METADATA
my_messenger_client-0.1.dist-info/WHEEL
my_messenger_client-0.1.dist-info/top_level.txt
my_messenger_client-0.1.dist-info/RECORD
