Metadata-Version: 2.1
Name: my-messenger-client
Version: 0.1
Summary: Client app with GUI to connect to private messenger server
Home-page: UNKNOWN
Author: Alexander Naumov
Author-email: myMessenger@gmail.com
License: UNKNOWN
Platform: UNKNOWN
Requires-Dist: PyQt5
Requires-Dist: sqlalchemy
Requires-Dist: pycryptodome
Requires-Dist: pycryptodomex
